LICENSE
README.md
setup.py
hein_robots/__init__.py
hein_robots/__version__.py
hein_robots/grids.py
hein_robots/managers.py
hein_robots/robotics.py
hein_robots/utils.py
hein_robots/vision.py
hein_robots.egg-info/PKG-INFO
hein_robots.egg-info/SOURCES.txt
hein_robots.egg-info/dependency_links.txt
hein_robots.egg-info/requires.txt
hein_robots.egg-info/top_level.txt
hein_robots/base/__init__.py
hein_robots/base/actuators.py
hein_robots/base/grippers.py
hein_robots/base/robot_arms.py
hein_robots/kinova/__init__.py
hein_robots/kinova/kinova_gen3.py
hein_robots/kinova/kinova_gripper.py
hein_robots/kinova/kinova_sequence.py
hein_robots/kinova/kortex.py
hein_robots/robodk/__init__.py
hein_robots/robodk/sim_arm.py
hein_robots/robotiq/__init__.py
hein_robots/robotiq/gripper.py
hein_robots/universal_robots/__init__.py
hein_robots/universal_robots/ur3.py
hein_robots/universal_robots/urscript_sequence.py
hein_robots/vention/__init__.py
hein_robots/vention/gantry.py