Metadata-Version: 2.1
Name: hein-robots
Version: 0.6.0
Summary: An easy-to-use package that provides a common interface for controlling robots used by the Hein Lab
Home-page: https://gitlab.com/heingroup/hein_robots
Author: Sean Clark
Author-email: sean@v13inc.com
License: MIT
Platform: UNKNOWN
Requires-Python: >=3.6.0
License-File: LICENSE
